MANIFEST.in
README.rst
requirements.txt
setup.cfg
setup.py
tika_app.egg-info/PKG-INFO
tika_app.egg-info/SOURCES.txt
tika_app.egg-info/dependency_links.txt
tika_app.egg-info/entry_points.txt
tika_app.egg-info/requires.txt
tika_app.egg-info/top_level.txt
tikapp/__init__.py
tikapp/__main__.py
tikapp/exceptions.py
tikapp/tikapp.py
tikapp/utils.py
tikapp/version.py