Metadata-Version: 1.1
Name: tika-app
Version: 1.3.0
Summary: Python client for Apache Tika App
Home-page: https://github.com/fedelemantuano/tika-app-python
Author: Fedele Mantuano
Author-email: mantuano.fedele@gmail.com
License: Apache License, Version 2.0
Keywords: tika,apache,toolkit
Platform: Linux
Classifier: License :: OSI Approved :: Apache Software License
Classifier: Intended Audience :: Developers
Classifier: Operating System :: OS Independent
Classifier: Programming Language :: Python
Classifier: Programming Language :: Python :: 2.7
Classifier: Programming Language :: Python :: 3
Classifier: Programming Language :: Python :: 3.3
Classifier: Programming Language :: Python :: 3.4
Classifier: Programming Language :: Python :: 3.5
